setup.py
cool_logging/__init__.py
cool_logging/__main__.py
cool_logging/formatters.py
cool_logging.egg-info/PKG-INFO
cool_logging.egg-info/SOURCES.txt
cool_logging.egg-info/dependency_links.txt
cool_logging.egg-info/requires.txt
cool_logging.egg-info/top_level.txt