Metadata-Version: 1.1
Name: cool-logging
Version: 0.3
Summary: Nice colorful formatter for Python logging
Home-page: https://github.com/rshk/cool-logging
Author: Samuele Santi
Author-email: samuele@samuelesanti.com
License: GNU General Public License v3 or later (GPLv3+)
Platform: UNKNOWN
Classifier: License :: OSI Approved :: GNU General Public License v3 or later (GPLv3+)
